Memory/memory.v
module memory ( 
    input clk,
    input [9:0] mem_addrs,
    input mem_read,
    input mem_write,
    input [31:0] write_data,
    output reg [31:0] read_data
);

reg [31:0] mem [1023:0];

always @(posedge clk) begin

    if (mem_write)
       mem[mem_addrs] <= write_data;
end

always@(*) begin
    
    if (mem_read)
       read_data = mem[mem_addrs];
    else
       read_data = 32'b0;
       
end

endmodule

Memory/memory_tb.v
`include "memory.v"
module memory_tb;

    reg clk;
    reg [9:0] mem_addrs;
    reg mem_read;
    reg mem_write;
    reg [31:0] write_data;
    wire [31:0] read_data;

    memory mem_inst (
        .clk(clk),
        .mem_addrs(mem_addrs),
        .mem_read(mem_read),
        .mem_write(mem_write),
        .write_data(write_data),
        .read_data(read_data)
    );

    // Clock generation
    always #5 clk = ~clk;

    initial begin
        $dumpfile("memory.vcd");
        $dumpvars(0,memory_tb);
        clk = 0;

        // Initial values
        mem_addrs = 10'd0;
        mem_read = 0;
        mem_write = 0;
        write_data = 32'd0;

        // WRITE: Store 12345678 at address 10
        #2;
        mem_addrs = 10'd10;
        write_data = 32'h12345678;
        mem_write = 1;
        #10;
        mem_write = 0;

        // READ: Read from address 10
        #2;
        mem_read = 1;
        #1;
        $display("Read data from addr 10: %h", read_data);
        mem_read = 0;

        // WRITE: Store deadbeef at address 20
        #2;
        mem_addrs = 10'd20;
        write_data = 32'hDEADBEEF;
        mem_write = 1;
        #10;
        mem_write = 0;

        // READ: Read from address 20
        #2;
        mem_addrs = 10'd20;
        mem_read = 1;
        #1;
        $display("Read data from addr 20: %h", read_data);
        mem_read = 0;

        $finish;
    end

endmodule

Memory/memory.vcd
$date
	Tue Apr 22 17:06:24 2025
$end
$version
	Icarus Verilog
$end
$timescale
	1s
$end
$scope module memory_tb $end
$var wire 32 ! read_data [31:0] $end
$var reg 1 " clk $end
$var reg 10 # mem_addrs [9:0] $end
$var reg 1 $ mem_read $end
$var reg 1 % mem_write $end
$var reg 32 & write_data [31:0] $end
$scope module mem_inst $end
$var wire 1 " clk $end
$var wire 10 ' mem_addrs [9:0] $end
$var wire 1 $ mem_read $end
$var wire 1 % mem_write $end
$var wire 32 ( write_data [31:0] $end
$var reg 32 ) read_data [31:0] $end
$upscope $end
$upscope $end
$enddefinitions $end
$comment Show the parameter values. $end
$dumpall
$end
#0
$dumpvars
b0 )
b0 (
b0 '
b0 &
0%
0$
b0 #
0"
b0 !
$end
#2
1%
b10010001101000101011001111000 &
b10010001101000101011001111000 (
b1010 #
b1010 '
#5
1"
#10
0"
#12
0%
#14
b10010001101000101011001111000 !
b10010001101000101011001111000 )
1$
#15
b0 !
b0 )
0$
1"
#17
1%
b11011110101011011011111011101111 &
b11011110101011011011111011101111 (
b10100 #
b10100 '
#20
0"
#25
1"
#27
0%
#29
b11011110101011011011111011101111 !
b11011110101011011011111011101111 )
1$
#30
b0 !
b0 )
0$
0"
